README.md
setup.cfg
setup.py
research/__init__.py
research.egg-info/PKG-INFO
research.egg-info/SOURCES.txt
research.egg-info/dependency_links.txt
research.egg-info/requires.txt
research.egg-info/top_level.txt
research/rl/__init__.py
research/rl/qlearning/__init__.py
research/rl/qlearning/basic/__init__.py
research/rl/qlearning/basic/utils.py
research/rl/qlearning/basic/qlearner_obs_act_seq/__init__.py
research/rl/qlearning/basic/qlearner_obs_act_seq/feature_transformer.py
research/rl/qlearning/basic/qlearner_obs_act_seq/qlearner_obs_act_seq.py
research/rl/qlearning/basic/qlearner_obs_seq/__init__.py
research/rl/qlearning/basic/qlearner_obs_seq/feature_transformer.py
research/rl/qlearning/basic/qlearner_obs_seq/qlearner_obs_seq.py
research/rl/qlearning/basic/qlearner_obs_single/__init__.py
research/rl/qlearning/basic/qlearner_obs_single/feature_transformer.py
research/rl/qlearning/basic/qlearner_obs_single/qlearner_obs_single.py
research/rl/qlearning/dqn/__init__.py
research/rl/qlearning/dqn/dqn_seq_obs/__init__.py
research/rl/qlearning/dqn/dqn_seq_obs/numpy_seq_dqn.py
research/rl/qlearning/dqn/dqn_seq_obs/tensorflow_seq_dqn.py
research/rl/qlearning/dqn/single_obs_dqn/__init__.py
research/rl/qlearning/dqn/single_obs_dqn/model.py
research/rl/qlearning/dqn/single_obs_dqn/numpy_dqn_obs_single.py